textutilsSohaib/__init__.py
textutilsSohaib/transformations.py
textutilsSohaib-1.1.0.dist-info/METADATA
textutilsSohaib-1.1.0.dist-info/WHEEL
textutilsSohaib-1.1.0.dist-info/top_level.txt
textutilsSohaib-1.1.0.dist-info/RECORD
